<annotation verified="yes">
  <folder>/Users/jkurz/git/models/research/annotations</folder>
  <filename>Santa_000000818.png</filename>
  <path>./images/santa/Santa_000000818.png</path>
  <source><database>Unknown</database></source>
  <size><width>360</width><height>320</height><depth>3</depth></size>
  <segmented>0</segmented>
  <object>
    <name>santa</name>
    <pose>Unspecified</pose>
    <truncated>0</truncated>
    <difficult>0</difficult>
      <bndbox>
        <xmin>207</xmin>
        <ymin>97</ymin>
        <xmax>292</xmax>
        <ymax>158</ymax>
      </bndbox>
  </object>
</annotation>